{"lastUpdate": 1669806974, "members": {"summerwlck": {"rank": "CHIEF", "contributed": 15100622, "lastSeen": 1668315431}, "FlapCakeToo": {"rank": "CHIEF", "contributed": 140630, "lastSeen": 1660120739}, "beewick": {"rank": "RECRUIT", "contributed": 463584, "lastSeen": 1662938624}, "sebwick": {"rank": "RECRUIT", "contributed": 28220, "lastSeen": 1574842615}, "_SkinnyFish_": {"rank": "RECRUITER", "contributed": 842233, "lastSeen": 1658027003}, "Brenden0404": {"rank": "RECRUIT", "contributed": 8371783, "lastSeen": 0}, "ChinnyChina1234": {"rank": "RECRUITER", "contributed": 4014219, "lastSeen": 1596932965}, "Neferou": {"rank": "RECRUIT", "contributed": 27968, "lastSeen": 1618588828}, "Skiddylicense04": {"rank": "RECRUITER", "contributed": 23625, "lastSeen": 1571636009}, "Brutal_Desires": {"rank": "RECRUIT", "contributed": 0, "lastSeen": 1587351696}, "PikaPikaTbnr": {"rank": "CHIEF", "contributed": 1519420, "lastSeen": 1640635038}, "Rafax011": {"rank": "RECRUIT", "contributed": 233254, "lastSeen": 1595274315}, "sheky090": {"rank": "RECRUIT", "contributed": 165528, "lastSeen": 1545793236}, "PuchaczMatek": {"rank": "RECRUIT", "contributed": 98839, "lastSeen": 1545540209}, "barek242": {"rank": "RECRUIT", "contributed": 1482, "lastSeen": 1545089896}, "TheDarkWeb": {"rank": "RECRUITER", "contributed": 1013496, "lastSeen": 1587190495}, "kirbyfofa768": {"rank": "CAPTAIN", "contributed": 5028209, "lastSeen": 1667216712}, "lilweeboi": {"rank": "RECRUIT", "contributed": 559, "lastSeen": 1574709693}, "doumaniac": {"rank": "CAPTAIN", "contributed": 587, "lastSeen": 1623381475}, "The_Isolated": {"rank": "OWNER", "contributed": 63216776, "lastSeen": 0}, "BardMann": {"rank": "CAPTAIN", "contributed": 19262331, "lastSeen": 1652229013}, "craftasaurus61": {"rank": "RECRUIT", "contributed": 78546, "lastSeen": 1663187518}, "Legolas0406": {"rank": "RECRUIT", "contributed": 2, "lastSeen": 1667975674}, "1HesamMega": {"rank": "RECRUIT", "contributed": 1337942, "lastSeen": 1669304470}, "cremenom": {"rank": "RECRUIT", "contributed": 32399, "lastSeen": 1666978676}, "3coooo": {"rank": "RECRUIT", "contributed": 59458, "lastSeen": 1666806355}, "PhoKing_MikeHawk": {"rank": "RECRUIT", "contributed": 21718, "lastSeen": 1667998879}, "ExL04": {"rank": "RECRUIT", "contributed": 202679, "lastSeen": 1668635855}}, "joined": {"_CallMeLegit": 1669159082, "_ShiiroChan": 1669159082, "Liezz": 1669159082, "TheGameHunter00": 1669159082, "Bensku1": 1669159083, "MrJonska": 1669159083, "sobol123": 1669159084, "woozy_face": 1669159084, "xXGeometricalXx": 1669159084, "Joshiemomo": 1669159084, "SugarMuch": 1669159086, "Jaaaash23": 1669159086, "1rd": 1669159086, "W4nted": 1669159086, "TJTheMonkey_": 1669159086, "EPISODE14": 1669159087, "dirtylyon": 1669159087, "summerwlck": 1669159092, "FlapCakeToo": 1669159092, "beewick": 1669159092, "sebwick": 1669159092, "_SkinnyFish_": 1669159092, "Brenden0404": 1669159092, "ChinnyChina1234": 1669159093, "Neferou": 1669159093, "Skiddylicense04": 1669159093, "Brutal_Desires": 1669159093, "PikaPikaTbnr": 1669159093, "Rafax011": 1669159093, "sheky090": 1669159094, "PuchaczMatek": 1669159094, "barek242": 1669159094, "TheDarkWeb": 1669159094, "kirbyfofa768": 1669159094, "lilweeboi": 1669159094, "doumaniac": 1669159094, "The_Isolated": 1669159095, "BardMann": 1669159095, "craftasaurus61": 1669159095, "Legolas0406": 1669159095, "1HesamMega": 1669159095, "cremenom": 1669159095, "3coooo": 1669159095, "PhoKing_MikeHawk": 1669159096, "ExL04": 1669159096}, "left": {"Wilberttt": {"leftAt": 1669159082, "rank": "OWNER"}, "KawaiiCutieUwU": {"leftAt": 1669159082, "rank": "CHIEF"}, "Azurra": {"leftAt": 1669159082, "rank": "RECRUIT"}, "ma1ding": {"leftAt": 1669159082, "rank": "CAPTAIN"}, "Edgy_Paper": {"leftAt": 1669159082, "rank": "STRATEGIST"}, "Ntwjvortex": {"leftAt": 1669159082, "rank": "RECRUIT"}, "Nacare": {"leftAt": 1669159082, "rank": "RECRUIT"}, "Chxshiya": {"leftAt": 1669159082, "rank": "RECRUIT"}, "kaiserthebest": {"leftAt": 1669159082, "rank": "RECRUIT"}, "_CallMeLegit": {"leftAt": 1669159084, "rank": "OWNER"}, "_ShiiroChan": {"leftAt": 1669159084, "rank": "CHIEF"}, "Liezz": {"leftAt": 1669159084, "rank": "CHIEF"}, "TheGameHunter00": {"leftAt": 1669159084, "rank": "RECRUIT"}, "Bensku1": {"leftAt": 1669159084, "rank": "OWNER"}, "MrJonska": {"leftAt": 1669159084, "rank": "CHIEF"}, "sobol123": {"leftAt": 1669159084, "rank": "RECRUIT"}, "woozy_face": {"leftAt": 1669159084, "rank": "RECRUIT"}, "xXGeometricalXx": {"leftAt": 1669159087, "rank": "OWNER"}, "Joshiemomo": {"leftAt": 1669159087, "rank": "RECRUIT"}, "SugarMuch": {"leftAt": 1669159096, "rank": "OWNER"}, "Jaaaash23": {"leftAt": 1669159096, "rank": "CAPTAIN"}, "1rd": {"leftAt": 1669159096, "rank": "CHIEF"}, "W4nted": {"leftAt": 1669159096, "rank": "CAPTAIN"}, "TJTheMonkey_": {"leftAt": 1669159096, "rank": "CAPTAIN"}, "EPISODE14": {"leftAt": 1669159096, "rank": "RECRUIT"}, "dirtylyon": {"leftAt": 1669159096, "rank": "RECRUIT"}}}