{"lastUpdate": 1698000647, "members": {"blaahman": {"rank": "RECRUIT", "contributed": 4312, "lastSeen": 0}, "ender_crafter101": {"rank": "RECRUIT", "contributed": 196, "lastSeen": 1447766122}, "Voidstar2": {"rank": "OWNER", "contributed": 43913, "lastSeen": 1698000647}, "_ReynTime_": {"rank": "RECRUIT", "contributed": 1559, "lastSeen": 1419993137}, "Orellan": {"rank": "RECRUIT", "contributed": 19107, "lastSeen": 1467269677}, "ThickWeenus": {"rank": "RECRUIT", "contributed": 349, "lastSeen": 1555052115}, "Meesknol": {"rank": "RECRUIT", "contributed": 2954, "lastSeen": 1572208788}, "Sylvieeeeee": {"rank": "RECRUIT", "contributed": 112617, "lastSeen": 1624961886}}, "joined": {}, "left": {}}