{"lastUpdate": 1670533802, "members": {"greeninja123": {"rank": "RECRUIT", "contributed": 123845, "lastSeen": 1523748645}, "birthe12": {"rank": "RECRUIT", "contributed": 0, "lastSeen": 1459014036}, "Kevkefuen123": {"rank": "RECRUIT", "contributed": 0, "lastSeen": 1640729812}, "JpSlime": {"rank": "RECRUIT", "contributed": 522, "lastSeen": 1500502348}, "NoHaxxJustDonuts": {"rank": "RECRUIT", "contributed": 93, "lastSeen": 1468366081}, "Splicey": {"rank": "RECRUIT", "contributed": 1951, "lastSeen": 0}, "21hollow27": {"rank": "OWNER", "contributed": 6101392, "lastSeen": 1666943366}, "endgameXp": {"rank": "CHIEF", "contributed": 2395963, "lastSeen": 1670562359}}, "joined": {}, "left": {}}