{"lastUpdate": 1677359723, "members": {"Crafter_77__": {"rank": "OWNER", "contributed": 3292593, "lastSeen": 1606908633}, "coolioth": {"rank": "CHIEF", "contributed": 19223, "lastSeen": 1594189864}, "iAmSoBadAtThis": {"rank": "CHIEF", "contributed": 3424567, "lastSeen": 1634371924}, "puffables": {"rank": "RECRUIT", "contributed": 30955, "lastSeen": 1670137384}, "CopperBoom": {"rank": "CAPTAIN", "contributed": 738164, "lastSeen": 1677359725}, "Crafting_AC": {"rank": "RECRUIT", "contributed": 347, "lastSeen": 1594382344}}, "joined": {"Crafter_77__": 1677359723, "coolioth": 1677359724, "iAmSoBadAtThis": 1677359724, "puffables": 1677359724, "CopperBoom": 1677359724, "Crafting_AC": 1677359725}, "left": {"9ober": {"leftAt": 1677359725, "rank": "RECRUIT"}, "fqu": {"leftAt": 1677359725, "rank": "RECRUIT"}, "Thunderrapid": {"leftAt": 1677359725, "rank": "RECRUITER"}, "Tactical_Roses": {"leftAt": 1677359725, "rank": "CAPTAIN"}, "ImaginePandaas": {"leftAt": 1677359725, "rank": "RECRUIT"}, "PredatorAlpha": {"leftAt": 1677359725, "rank": "RECRUIT"}, "williamlmao": {"leftAt": 1677359725, "rank": "OWNER"}, "J0hnCena": {"leftAt": 1677359725, "rank": "RECRUIT"}}}