{"lastUpdate": 1695163193, "members": {"Muulm": {"rank": "OWNER", "contributed": 586389, "lastSeen": 1618025481}, "AutoJan": {"rank": "RECRUIT", "contributed": 71549, "lastSeen": 0}, "ReegL": {"rank": "RECRUIT", "contributed": 568012, "lastSeen": 1616686517}, "HoneyFoo": {"rank": "RECRUIT", "contributed": 165469, "lastSeen": 1625797804}, "Rynth": {"rank": "RECRUIT", "contributed": 34781, "lastSeen": 1625368428}, "urbentmate": {"rank": "RECRUIT", "contributed": 972495, "lastSeen": 1682611232}, "LuccyLY": {"rank": "RECRUIT", "contributed": 94851, "lastSeen": 1668642918}}, "joined": {}, "left": {}}