{"lastUpdate": 1671765243, "members": {"Sebiann": {"rank": "CHIEF", "contributed": 15795377, "lastSeen": 1671454513}, "JumperRaptor": {"rank": "RECRUIT", "contributed": 59713, "lastSeen": 1611628249}, "AlexRuna": {"rank": "RECRUIT", "contributed": 28, "lastSeen": 1608771185}, "Lolface_9": {"rank": "RECRUIT", "contributed": 107253, "lastSeen": 1627272635}, "Sandur_": {"rank": "RECRUIT", "contributed": 60924, "lastSeen": 1627077676}, "ThePugProtector": {"rank": "RECRUIT", "contributed": 36418, "lastSeen": 1626946443}, "Hyper_Pigeon": {"rank": "RECRUIT", "contributed": 72559, "lastSeen": 1627121275}, "DJ_PBnJ": {"rank": "RECRUIT", "contributed": 27052, "lastSeen": 1626946961}, "BlackRose_1": {"rank": "RECRUIT", "contributed": 1746, "lastSeen": 1639347028}, "Hoi_A": {"rank": "OWNER", "contributed": 742944, "lastSeen": 1671752287}, "AlyssaGamez": {"rank": "CHIEF", "contributed": 108332, "lastSeen": 1671765243}}, "joined": {}, "left": {}}