{"members": {"Xcis": {"rank": "CHIEF", "contributed": 212, "lastSeen": 1676685433}, "Irony": {"rank": "OWNER", "contributed": 0, "lastSeen": 1676848510}}, "joined": {"Yekes": 1668149743, "kingkojiro": 1668277369, "WynnPenguin": 1668342963, "Torbleron": 1668552023, "ichigo_minecraft": 1668716378, "FallenRamen": 1668736012, "TaylorIsGreat": 1668746799, "Omnivi": 1668804026, "Wizchad": 1668957479, "LumpOfSeal": 1669040185, "MagecoreLP": 1669043988, "VoisD": 1669045342, "TheSlyMiner": 1669045342, "GuyLupo69": 1669047983, "Jesa1": 1669061918, "Minnoch": 1669081505, "Misguild": 1669081505, "Hoshi_No_Kaabii": 1669086700, "Chickkeen": 1669098239, "Jurrior": 1669141390, "Niesi": 1669196564, "L0rD_B33RuS": 1669223704, "MrSheldon": 1669230824, "AndreScout": 1669235913, "Shrils": 1669325814, "_Onyon": 1669493831, "Scoutje313": 1669544246, "KaiTheSergal": 1669574475, "UncUnc": 1669771603, "ptoooooooo": 1669829825, "piggylover6": 1669905318, "Spirit_Sceptre": 1669973610, "Edrin_": 1669990106, "BobbyRon": 1670037001, "haruwu_owo": 1670074516, "Sweet64": 1670166662, "FezbearTheBear": 1670249421, "LuqDude": 1670297763, "ThaDeny": 1670335699, "IkMagJouNiet": 1670337338, "WinBeta": 1670434543, "unrealphantom": 1670620229, "WayaBoy": 1670643580, "BurdsIQ": 1670816594, "mrelderson": 1670898137, "Moogled": 1670908243, "MythicMan123": 1670909741, "Uldoc": 1670969536, "Mayka": 1671046690, "Strwberries": 1671093624, "CudlessTheBear": 1671104108, "Dynam8": 1671120849, "soccerbomb3": 1671122903, "erchh": 1671207154, "VBilla": 1671214393, "Kxudraco8341": 1671225218, "lso": 1671225218, "GOG100": 1671289940, "Kekuraz": 1671334640, "vUniity": 1671487982, "404l": 1671568765, "Stellunasol": 1671568765, "RiverThe21st": 1671572122, "SirBino": 1671574231, "Conncr": 1671705512, "Khappazix": 1671723439, "Look12": 1671842201, "xPartyAnimal": 1671851621, "wacksun": 1671912632, "Merkena": 1672023121, "GOLDN1TE": 1672040196, "RAGN0S": 1672060595, "Badcraft1": 1672161062, "LostGuyGT": 1672173554, "RaphaelRose": 1672205783, "Nova007": 1672243940, "Quackk": 1672342681, "VaKeMeUp": 1672411053, "Halbarad_": 1672497558, "Slouch": 1672690388, "FurryStyle": 1672798534, "Majorenn": 1672843141, "_Eldorin": 1672868349, "sandy666": 1672868349, "Penguinges": 1672888403, "MeltedMagma": 1672918458, "ShadowStormPlayz": 1672931468, "LogicalSpaghetti": 1672954738, "uwuOoze": 1672980016, "HJPoLLi": 1672990553, "SeaPeach": 1672990554, "IAmAGiantNoob": 1673098641, "Unluckyest": 1673492117, "jittermat": 1673576308, "Chafd": 1673602567, "EchoHD_": 1673609659, "AphoticGoblin": 1673644317, "SpookieGG": 1673787146, "LordRotharoth": 1673820687, "E_Kappa": 1673829687, "Castalyn": 1673829687, "ProDucktive": 1673856811, "BrainControl": 1673860284, "ZyTexGamer": 1673871279, "Redex27": 1673879791, "Crowmore": 1673897832, "Ticxo": 1673900046, "Bell789": 1673991474, "CasualBridger": 1674081456, "Its_Me_Vince": 1674128191, "Salibian": 1674335473, "Gup0": 1674387427, "Dreadddddddddddd": 1674401792, "MikiTq": 1674542342, "noneke": 1674598285, "Lloydypoo": 1674624871, "Roof88": 1674649004, "vivi06063": 1675141916, "AlphaDegenerate": 1675348643, "lil_cotton_swab": 1675350690, "TeenTykan": 1675364970, "_link_2012_": 1675453023, "IcingXsugar": 1675613650, "Zepic32": 1675701982, "rmminemonster": 1675741028, "Banguette": 1675816825, "CloaK_Daetol": 1675822813, "Chraosulus": 1675869165, "migu31": 1675874959, "damocleas": 1675887142, "Tob_1": 1675953396, "tuoleiqwq": 1676088846, "TomMeadow": 1676200224, "kmaxi": 1676272177, "phandu1907": 1676545892, "Imrohan": 1676736801, "Follets": 1676763586, "Xcis": 1676834037, "Irony": 1676834037}, "left": {"WynnPenguin": {"leftAt": 1668346222, "rank": "RECRUIT"}, "unrealphantom": {"leftAt": 1672848904, "rank": "RECRUIT"}, "SQ0TT": {"leftAt": 1668709358, "rank": "CAPTAIN"}, "Obi": {"leftAt": 1668709358, "rank": "CAPTAIN"}, "Flippone": {"leftAt": 1668709358, "rank": "RECRUITER"}, "Infinting": {"leftAt": 1668709358, "rank": "RECRUITER"}, "Wizchad": {"leftAt": 1669040185, "rank": "STRATEGIST"}, "Tobler_Inc": {"leftAt": 1668709358, "rank": "RECRUIT"}, "Omnivi": {"leftAt": 1668813506, "rank": "RECRUIT"}, "PigeonFanatic": {"leftAt": 1669040185, "rank": "RECRUIT"}, "CoduPotato31": {"leftAt": 1669040185, "rank": "RECRUIT"}, "ValentineX": {"leftAt": 1669040185, "rank": "RECRUIT"}, "Grubenkrieger": {"leftAt": 1669040185, "rank": "RECRUIT"}, "OnePlusTwoIsFour": {"leftAt": 1669041578, "rank": "RECRUIT"}, "_X_BananaMan_X_": {"leftAt": 1669043988, "rank": "RECRUITER"}, "_Duzzel_": {"leftAt": 1669043988, "rank": "RECRUIT"}, "BigAsianJack": {"leftAt": 1669181835, "rank": "RECRUITER"}, "1Bos": {"leftAt": 1669184510, "rank": "RECRUITER"}, "JordanTowels": {"leftAt": 1669203422, "rank": "RECRUIT"}, "DeepBlue_i7": {"leftAt": 1669203422, "rank": "RECRUIT"}, "MeteorMes": {"leftAt": 1669225015, "rank": "STRATEGIST"}, "Simulation21": {"leftAt": 1669450872, "rank": "RECRUIT"}, "woofly": {"leftAt": 1669544246, "rank": "RECRUITER"}, "GalacticBat": {"leftAt": 1669573204, "rank": "CAPTAIN"}, "_qe": {"leftAt": 1669573204, "rank": "CAPTAIN"}, "wholg": {"leftAt": 1669581469, "rank": "RECRUITER"}, "sworii": {"leftAt": 1669903760, "rank": "RECRUITER"}, "1nn8": {"leftAt": 1669903760, "rank": "RECRUIT"}, "ichigo_minecraft": {"leftAt": 1669903760, "rank": "RECRUIT"}, "get_spookd": {"leftAt": 1670019064, "rank": "RECRUITER"}, "BrainControl": {"leftAt": 1676834037, "rank": "RECRUIT"}, "Caperised": {"leftAt": 1670144906, "rank": "RECRUITER"}, "MikiTq": {"leftAt": 1676834037, "rank": "STRATEGIST"}, "TheSlyMiner": {"leftAt": 1670272605, "rank": "RECRUIT"}, "ptoooooooo": {"leftAt": 1670297763, "rank": "RECRUIT"}, "kingkojiro": {"leftAt": 1670337338, "rank": "RECRUIT"}, "AskTaco": {"leftAt": 1670350493, "rank": "RECRUIT"}, "PanfriedPanda": {"leftAt": 1670620229, "rank": "STRATEGIST"}, "GuyLupo69": {"leftAt": 1670620229, "rank": "RECRUIT"}, "Loilipop": {"leftAt": 1670695947, "rank": "CAPTAIN"}, "1_am_a_penguin": {"leftAt": 1670744206, "rank": "RECRUIT"}, "5cyth3": {"leftAt": 1670816594, "rank": "RECRUITER"}, "stunnii": {"leftAt": 1670908243, "rank": "CAPTAIN"}, "jittermat": {"leftAt": 1676834037, "rank": "RECRUIT"}, "Harolth": {"leftAt": 1671046690, "rank": "RECRUITER"}, "ToNoize": {"leftAt": 1671093624, "rank": "STRATEGIST"}, "a6o": {"leftAt": 1671093624, "rank": "RECRUIT"}, "Jesa1": {"leftAt": 1671093624, "rank": "RECRUIT"}, "UncUnc": {"leftAt": 1671093624, "rank": "RECRUIT"}, "PartlySunny": {"leftAt": 1671204979, "rank": "RECRUITER"}, "ZeDcHar": {"leftAt": 1671204979, "rank": "RECRUIT"}, "FallenRamen": {"leftAt": 1671204979, "rank": "RECRUIT"}, "ThaDeny": {"leftAt": 1671204979, "rank": "RECRUITER"}, "DaedStatic": {"leftAt": 1671289940, "rank": "CAPTAIN"}, "Spirit_Sceptre": {"leftAt": 1671289940, "rank": "RECRUIT"}, "debliniak": {"leftAt": 1671468637, "rank": "RECRUITER"}, "xDuskyx": {"leftAt": 1671468637, "rank": "RECRUIT"}, "cheesetrap": {"leftAt": 1671568765, "rank": "CAPTAIN"}, "Shrils": {"leftAt": 1671568765, "rank": "RECRUIT"}, "Moogled": {"leftAt": 1671568765, "rank": "RECRUIT"}, "Zer0Tang0": {"leftAt": 1671574231, "rank": "RECRUITER"}, "WayaBoy": {"leftAt": 1671575766, "rank": "CHIEF"}, "Jurrior": {"leftAt": 1671761375, "rank": "RECRUIT"}, "IkMagJouNiet": {"leftAt": 1671826505, "rank": "RECRUIT"}, "SpikefulCacti": {"leftAt": 1672159633, "rank": "CAPTAIN"}, "11_Artanis_11": {"leftAt": 1672159633, "rank": "RECRUITER"}, "damocleas": {"leftAt": 1676834037, "rank": "RECRUIT"}, "piggylover6": {"leftAt": 1672159633, "rank": "RECRUIT"}, "Yekes": {"leftAt": 1672243940, "rank": "RECRUIT"}, "RaphaelRose": {"leftAt": 1672279957, "rank": "RECRUIT"}, "Niesi": {"leftAt": 1672316166, "rank": "RECRUIT"}, "VoisD": {"leftAt": 1672400165, "rank": "RECRUIT"}, "Slouch": {"leftAt": 1672691843, "rank": "RECRUIT"}, "Minnoch": {"leftAt": 1672778186, "rank": "RECRUIT"}, "___Epiphany___": {"leftAt": 1672848904, "rank": "RECRUITER"}, "MrSheldon": {"leftAt": 1672848904, "rank": "RECRUIT"}, "Khappazix": {"leftAt": 1672856123, "rank": "RECRUIT"}, "Maracs": {"leftAt": 1672888403, "rank": "STRATEGIST"}, "31Yoshi31": {"leftAt": 1672921017, "rank": "RECRUITER"}, "L0rD_B33RuS": {"leftAt": 1672921017, "rank": "RECRUIT"}, "Kxudraco8341": {"leftAt": 1672985595, "rank": "RECRUIT"}, "LostGuyGT": {"leftAt": 1672985595, "rank": "RECRUIT"}, "Chickkeen": {"leftAt": 1672999836, "rank": "RECRUIT"}, "Hoshi_No_Kaabii": {"leftAt": 1673450345, "rank": "RECRUIT"}, "LuqDude": {"leftAt": 1673576308, "rank": "RECRUIT"}, "Mayka": {"leftAt": 1673602567, "rank": "RECRUIT"}, "MappinHD": {"leftAt": 1673609659, "rank": "RECRUIT"}, "VaKeMeUp": {"leftAt": 1673609659, "rank": "RECRUIT"}, "CudlessTheBear": {"leftAt": 1673710706, "rank": "CAPTAIN"}, "soccerbomb3": {"leftAt": 1673811447, "rank": "RECRUIT"}, "Alberttron420": {"leftAt": 1673817208, "rank": "RECRUIT"}, "lso": {"leftAt": 1673817208, "rank": "RECRUIT"}, "GOG100": {"leftAt": 1673817208, "rank": "RECRUIT"}, "Look12": {"leftAt": 1673817208, "rank": "RECRUIT"}, "KaiTheSergal": {"leftAt": 1673871279, "rank": "RECRUIT"}, "Nova007": {"leftAt": 1673871279, "rank": "RECRUIT"}, "GOLDN1TE": {"leftAt": 1673892907, "rank": "RECRUIT"}, "Aleksander299": {"leftAt": 1673894433, "rank": "RECRUITER"}, "xPartyAnimal": {"leftAt": 1673940845, "rank": "RECRUIT"}, "WinBeta": {"leftAt": 1674076295, "rank": "RECRUIT"}, "Conncr": {"leftAt": 1674076295, "rank": "RECRUIT"}, "SirBino": {"leftAt": 1674335473, "rank": "RECRUIT"}, "Quackk": {"leftAt": 1674387427, "rank": "RECRUIT"}, "sandy666": {"leftAt": 1674387427, "rank": "RECRUIT"}, "Edrin_": {"leftAt": 1674542342, "rank": "RECRUIT"}, "LumpOfSeal": {"leftAt": 1674598285, "rank": "RECRUIT"}, "Halbarad_": {"leftAt": 1674598285, "rank": "RECRUIT"}, "FurryStyle": {"leftAt": 1674598285, "rank": "RECRUIT"}, "MeltedMagma": {"leftAt": 1674958792, "rank": "RECRUIT"}, "Uldoc": {"leftAt": 1675346962, "rank": "RECRUIT"}, "Majorenn": {"leftAt": 1675346962, "rank": "RECRUIT"}, "HJPoLLi": {"leftAt": 1675346962, "rank": "RECRUIT"}, "Chafd": {"leftAt": 1675346962, "rank": "RECRUIT"}, "Whaphle": {"leftAt": 1675609831, "rank": "STRATEGIST"}, "Strwberries": {"leftAt": 1675692650, "rank": "RECRUIT"}, "Kekuraz": {"leftAt": 1675692650, "rank": "RECRUIT"}, "404l": {"leftAt": 1675692650, "rank": "RECRUIT"}, "wacksun": {"leftAt": 1675692650, "rank": "RECRUIT"}, "Merkena": {"leftAt": 1675692650, "rank": "RECRUIT"}, "SpookieGG": {"leftAt": 1675692650, "rank": "RECRUIT"}, "Its_Me_Vince": {"leftAt": 1675692650, "rank": "RECRUIT"}, "AphoticGoblin": {"leftAt": 1675953396, "rank": "RECRUIT"}, "vUniity": {"leftAt": 1676088846, "rank": "RECRUIT"}, "Dynam8": {"leftAt": 1676194618, "rank": "RECRUIT"}, "uwuOoze": {"leftAt": 1676233024, "rank": "RECRUIT"}, "Uniimog": {"leftAt": 1676241492, "rank": "RECRUITER"}, "Salibian": {"leftAt": 1676730991, "rank": "RECRUIT"}, "noneke": {"leftAt": 1676730991, "rank": "RECRUIT"}, "CloaK_Daetol": {"leftAt": 1676797889, "rank": "RECRUIT"}, "WoodCreature": {"leftAt": 1676834037, "rank": "CHIEF"}, "ArchoKast": {"leftAt": 1676834037, "rank": "CHIEF"}, "WeaponMerchant": {"leftAt": 1676834037, "rank": "CHIEF"}, "Aqualost": {"leftAt": 1676834037, "rank": "STRATEGIST"}, "SonnyVA": {"leftAt": 1676834037, "rank": "CHIEF"}, "CuzImTimer": {"leftAt": 1676834037, "rank": "STRATEGIST"}, "LordGonner": {"leftAt": 1676834037, "rank": "OWNER"}, "VireVeonix": {"leftAt": 1676834037, "rank": "CHIEF"}, "crturtle": {"leftAt": 1676834037, "rank": "CHIEF"}, "PolarBaeJr": {"leftAt": 1676834037, "rank": "CHIEF"}, "t_q": {"leftAt": 1676834037, "rank": "CAPTAIN"}, "TheSilverTide": {"leftAt": 1676834037, "rank": "RECRUITER"}, "Gatsy": {"leftAt": 1676834037, "rank": "STRATEGIST"}, "skellybone01": {"leftAt": 1676834037, "rank": "STRATEGIST"}, "ExtraLemonZest": {"leftAt": 1676834037, "rank": "STRATEGIST"}, "fishcute": {"leftAt": 1676834037, "rank": "RECRUITER"}, "Chqrish": {"leftAt": 1676834037, "rank": "STRATEGIST"}, "Deadly_King": {"leftAt": 1676834037, "rank": "CAPTAIN"}, "FeodorRomanov": {"leftAt": 1676834037, "rank": "STRATEGIST"}, "Ch1lde": {"leftAt": 1676834037, "rank": "STRATEGIST"}, "_GoldenShadow": {"leftAt": 1676834037, "rank": "CHIEF"}, "XH": {"leftAt": 1676834037, "rank": "RECRUITER"}, "Ashwey": {"leftAt": 1676834037, "rank": "STRATEGIST"}, "Nukewarmachine": {"leftAt": 1676834037, "rank": "STRATEGIST"}, "RagingFury1": {"leftAt": 1676834037, "rank": "RECRUIT"}, "Barled": {"leftAt": 1676834037, "rank": "STRATEGIST"}, "Alphatoxxx": {"leftAt": 1676834037, "rank": "STRATEGIST"}, "rikplays": {"leftAt": 1676834037, "rank": "RECRUITER"}, "GrizzlyChicken_": {"leftAt": 1676834037, "rank": "STRATEGIST"}, "howl888": {"leftAt": 1676834037, "rank": "CAPTAIN"}, "lonteina": {"leftAt": 1676834037, "rank": "CAPTAIN"}, "czad": {"leftAt": 1676834037, "rank": "STRATEGIST"}, "TNTLoveMe": {"leftAt": 1676834037, "rank": "STRATEGIST"}, "Myrmace": {"leftAt": 1676834037, "rank": "CAPTAIN"}, "MemeBard": {"leftAt": 1676834037, "rank": "CHIEF"}, "bukname1069": {"leftAt": 1676834037, "rank": "STRATEGIST"}, "Suhzie": {"leftAt": 1676834037, "rank": "STRATEGIST"}, "Kewbin": {"leftAt": 1676834037, "rank": "STRATEGIST"}, "Woealer": {"leftAt": 1676834037, "rank": "STRATEGIST"}, "NcMugget": {"leftAt": 1676834037, "rank": "RECRUITER"}, "ShamanOnly": {"leftAt": 1676834037, "rank": "RECRUITER"}, "D1uLaSing": {"leftAt": 1676834037, "rank": "RECRUITER"}, "dogwqter": {"leftAt": 1676834037, "rank": "RECRUITER"}, "Vaxture": {"leftAt": 1676834037, "rank": "CAPTAIN"}, "Balazskah": {"leftAt": 1676834037, "rank": "RECRUITER"}, "Glacade": {"leftAt": 1676834037, "rank": "CAPTAIN"}, "Aeroless": {"leftAt": 1676834037, "rank": "RECRUITER"}, "MudkipNinja": {"leftAt": 1676834037, "rank": "RECRUITER"}, "5a7": {"leftAt": 1676834037, "rank": "CAPTAIN"}, "Ninobf": {"leftAt": 1676834037, "rank": "CAPTAIN"}, "alproy": {"leftAt": 1676834037, "rank": "RECRUITER"}, "Meek_ANTIFUN": {"leftAt": 1676834037, "rank": "RECRUITER"}, "Corona_Weedus": {"leftAt": 1676834037, "rank": "STRATEGIST"}, "PokemonGamer11": {"leftAt": 1676834037, "rank": "STRATEGIST"}, "lindafelix": {"leftAt": 1676834037, "rank": "STRATEGIST"}, "Mesyder": {"leftAt": 1676834037, "rank": "RECRUITER"}, "DarkofFire": {"leftAt": 1676834037, "rank": "RECRUIT"}, "Torbleron": {"leftAt": 1676834037, "rank": "RECRUIT"}, "TaylorIsGreat": {"leftAt": 1676834037, "rank": "RECRUIT"}, "MagecoreLP": {"leftAt": 1676834037, "rank": "RECRUIT"}, "Misguild": {"leftAt": 1676834037, "rank": "RECRUIT"}, "AndreScout": {"leftAt": 1676834037, "rank": "RECRUIT"}, "_Onyon": {"leftAt": 1676834037, "rank": "RECRUIT"}, "Scoutje313": {"leftAt": 1676834037, "rank": "RECRUIT"}, "BobbyRon": {"leftAt": 1676834037, "rank": "RECRUIT"}, "haruwu_owo": {"leftAt": 1676834037, "rank": "RECRUIT"}, "Sweet64": {"leftAt": 1676834037, "rank": "RECRUIT"}, "FezbearTheBear": {"leftAt": 1676834037, "rank": "RECRUIT"}, "BurdsIQ": {"leftAt": 1676834037, "rank": "RECRUITER"}, "mrelderson": {"leftAt": 1676834037, "rank": "RECRUIT"}, "MythicMan123": {"leftAt": 1676834037, "rank": "RECRUIT"}, "erchh": {"leftAt": 1676834037, "rank": "RECRUIT"}, "VBilla": {"leftAt": 1676834037, "rank": "RECRUIT"}, "Stellunasol": {"leftAt": 1676834037, "rank": "RECRUIT"}, "RiverThe21st": {"leftAt": 1676834037, "rank": "RECRUIT"}, "RAGN0S": {"leftAt": 1676834037, "rank": "RECRUIT"}, "Badcraft1": {"leftAt": 1676834037, "rank": "RECRUIT"}, "_Eldorin": {"leftAt": 1676834037, "rank": "RECRUIT"}, "Penguinges": {"leftAt": 1676834037, "rank": "RECRUIT"}, "ShadowStormPlayz": {"leftAt": 1676834037, "rank": "RECRUIT"}, "LogicalSpaghetti": {"leftAt": 1676834037, "rank": "RECRUIT"}, "SeaPeach": {"leftAt": 1676834037, "rank": "RECRUIT"}, "IAmAGiantNoob": {"leftAt": 1676834037, "rank": "RECRUIT"}, "Unluckyest": {"leftAt": 1676834037, "rank": "RECRUIT"}, "EchoHD_": {"leftAt": 1676834037, "rank": "RECRUIT"}, "LordRotharoth": {"leftAt": 1676834037, "rank": "RECRUIT"}, "E_Kappa": {"leftAt": 1676834037, "rank": "RECRUIT"}, "Castalyn": {"leftAt": 1676834037, "rank": "RECRUIT"}, "ProDucktive": {"leftAt": 1676834037, "rank": "RECRUIT"}, "ZyTexGamer": {"leftAt": 1676834037, "rank": "RECRUIT"}, "Redex27": {"leftAt": 1676834037, "rank": "RECRUIT"}, "Crowmore": {"leftAt": 1676834037, "rank": "RECRUIT"}, "Ticxo": {"leftAt": 1676834037, "rank": "RECRUIT"}, "Bell789": {"leftAt": 1676834037, "rank": "RECRUIT"}, "CasualBridger": {"leftAt": 1676834037, "rank": "RECRUIT"}, "Gup0": {"leftAt": 1676834037, "rank": "RECRUIT"}, "Dreadddddddddddd": {"leftAt": 1676834037, "rank": "RECRUIT"}, "Lloydypoo": {"leftAt": 1676834037, "rank": "RECRUIT"}, "Roof88": {"leftAt": 1676834037, "rank": "RECRUIT"}, "vivi06063": {"leftAt": 1676834037, "rank": "RECRUIT"}, "AlphaDegenerate": {"leftAt": 1676834037, "rank": "RECRUIT"}, "lil_cotton_swab": {"leftAt": 1676834037, "rank": "RECRUIT"}, "TeenTykan": {"leftAt": 1676834037, "rank": "RECRUIT"}, "_link_2012_": {"leftAt": 1676834037, "rank": "RECRUIT"}, "IcingXsugar": {"leftAt": 1676834037, "rank": "RECRUIT"}, "Zepic32": {"leftAt": 1676834037, "rank": "RECRUIT"}, "rmminemonster": {"leftAt": 1676834037, "rank": "RECRUIT"}, "Banguette": {"leftAt": 1676834037, "rank": "RECRUIT"}, "Chraosulus": {"leftAt": 1676834037, "rank": "RECRUIT"}, "migu31": {"leftAt": 1676834037, "rank": "RECRUIT"}, "Tob_1": {"leftAt": 1676834037, "rank": "RECRUIT"}, "tuoleiqwq": {"leftAt": 1676834037, "rank": "RECRUIT"}, "TomMeadow": {"leftAt": 1676834037, "rank": "RECRUIT"}, "kmaxi": {"leftAt": 1676834037, "rank": "RECRUIT"}, "phandu1907": {"leftAt": 1676834037, "rank": "RECRUIT"}, "Imrohan": {"leftAt": 1676834037, "rank": "RECRUIT"}, "Follets": {"leftAt": 1676834037, "rank": "RECRUIT"}}, "lastUpdate": 1676848510}