{"lastUpdate": 1698085803, "members": {"Evanlynn": {"rank": "OWNER", "contributed": 8371569, "lastSeen": 1664926626}, "_Maevie": {"rank": "CHIEF", "contributed": 0, "lastSeen": 1617681267}, "Lilbisho": {"rank": "CHIEF", "contributed": 0, "lastSeen": 1696802240}, "Regenboogkots96": {"rank": "CHIEF", "contributed": 0, "lastSeen": 1612243483}, "Nivla": {"rank": "CHIEF", "contributed": 1505018, "lastSeen": 1664043838}, "Cricketas": {"rank": "CHIEF", "contributed": 10977, "lastSeen": 1698085803}}, "joined": {}, "left": {"Regenboogkots69": {"leftAt": 1698061373, "rank": "CHIEF"}}}