{"lastUpdate": 1698722507, "members": {"KoshiCookie": {"rank": "OWNER", "contributed": 3258059, "lastSeen": 1646394406}, "eGrill76": {"rank": "CAPTAIN", "contributed": 32465, "lastSeen": 1681778177}, "bo4524": {"rank": "CHIEF", "contributed": 10095025, "lastSeen": 1698722507}, "Offline_Bear": {"rank": "CAPTAIN", "contributed": 272947, "lastSeen": 1655425000}, "KawaiiPotoes": {"rank": "RECRUITER", "contributed": 169611, "lastSeen": 1585970481}, "MkawsomeDJ": {"rank": "RECRUIT", "contributed": 605, "lastSeen": 0}, "KYLETHEGREAT9": {"rank": "RECRUIT", "contributed": 0, "lastSeen": 1663514695}, "LPTogether2014": {"rank": "RECRUIT", "contributed": 12930, "lastSeen": 1669182192}, "Souru_TV": {"rank": "RECRUIT", "contributed": 232497, "lastSeen": 1622361492}, "Brynnakat": {"rank": "RECRUIT", "contributed": 86, "lastSeen": 1631005069}}, "joined": {"hc1219": 1669182182, "OR_IN": 1669182182, "Bradwurst_": 1669182182, "jakethesnake69": 1669182183, "KielKyoko": 1669182183, "check080": 1669182183, "PelicanHurricane": 1669182183, "KoshiCookie": 1669182186, "eGrill76": 1669182186, "bo4524": 1669182186, "Offline_Bear": 1669182187, "KawaiiPotoes": 1669182187, "MkawsomeDJ": 1669182187, "KYLETHEGREAT9": 1669182187, "LPTogether2014": 1669182187, "Souru_TV": 1669182188, "Brynnakat": 1669182188}, "left": {"Zoelisha": {"leftAt": 1669182183, "rank": "RECRUIT"}, "MentalStatus": {"leftAt": 1669182183, "rank": "RECRUITER"}, "Ralie": {"leftAt": 1669182183, "rank": "RECRUIT"}, "Sorcellerie": {"leftAt": 1669182183, "rank": "OWNER"}, "Fiorire": {"leftAt": 1669182183, "rank": "STRATEGIST"}, "Tharshie": {"leftAt": 1669182183, "rank": "RECRUIT"}, "tabii": {"leftAt": 1669182183, "rank": "RECRUIT"}, "apaulled": {"leftAt": 1669182183, "rank": "CHIEF"}, "constelacion": {"leftAt": 1669182183, "rank": "CHIEF"}, "TeknoPsycho": {"leftAt": 1669182183, "rank": "RECRUIT"}, "Lbby": {"leftAt": 1669182183, "rank": "RECRUIT"}, "Snowys": {"leftAt": 1669182183, "rank": "RECRUIT"}, "hc1219": {"leftAt": 1669182188, "rank": "CHIEF"}, "OR_IN": {"leftAt": 1669182188, "rank": "CHIEF"}, "Bradwurst_": {"leftAt": 1669182188, "rank": "RECRUIT"}, "jakethesnake69": {"leftAt": 1669182188, "rank": "RECRUIT"}, "KielKyoko": {"leftAt": 1669182188, "rank": "RECRUIT"}, "check080": {"leftAt": 1669182188, "rank": "RECRUIT"}, "PelicanHurricane": {"leftAt": 1669182188, "rank": "OWNER"}}}