{"lastUpdate": 1692087388, "members": {"Voidrim": {"rank": "OWNER", "contributed": 0, "lastSeen": 1692056791}, "kal_iuchka": {"rank": "CHIEF", "contributed": 0, "lastSeen": 1691941511}, "Shinoa__": {"rank": "CHIEF", "contributed": 0, "lastSeen": 1692035495}, "catgirlAnd": {"rank": "RECRUIT", "contributed": 0, "lastSeen": 1692048007}, "Cl_oN": {"rank": "RECRUIT", "contributed": 0, "lastSeen": 1690651309}, "catgirlvoidrim": {"rank": "RECRUIT", "contributed": 95, "lastSeen": 1692030073}, "AnEnderNon": {"rank": "CHIEF", "contributed": 0, "lastSeen": 1690758520}, "ElleOfTheNether": {"rank": "RECRUITER", "contributed": 0, "lastSeen": 1692087388}, "mattiskwl": {"rank": "RECRUITER", "contributed": 0, "lastSeen": 1691234019}, "Star_Shelly": {"rank": "RECRUIT", "contributed": 211, "lastSeen": 1692087388}}, "joined": {"catgirlAnd": 1689555486, "Cl_oN": 1689599520, "catgirlvoidrim": 1690635321, "AnEnderNon": 1690730303, "ElleOfTheNether": 1691007966, "CaptanCrunch": 1691036321, "mattiskwl": 1691230637, "Star_Shelly": 1691918064}, "left": {"CaptanCrunch": {"leftAt": 1691407083, "rank": "RECRUIT"}}}