{"lastUpdate": 1674911741, "members": {"Ryo_catom": {"rank": "OWNER", "contributed": 38354949, "lastSeen": 1674897017}, "josei456": {"rank": "STRATEGIST", "contributed": 10926837, "lastSeen": 1674889681}, "kirbyRRR": {"rank": "CAPTAIN", "contributed": 427, "lastSeen": 1667074304}, "smilekun": {"rank": "CAPTAIN", "contributed": 1499562, "lastSeen": 1674897017}, "Soichiro1000": {"rank": "CHIEF", "contributed": 1353979, "lastSeen": 1674887884}, "refrigerant": {"rank": "CAPTAIN", "contributed": 0, "lastSeen": 1674895050}, "Ere256": {"rank": "STRATEGIST", "contributed": 0, "lastSeen": 1671264863}, "KTcompany": {"rank": "RECRUIT", "contributed": 1557, "lastSeen": 1674382305}, "mokan": {"rank": "RECRUIT", "contributed": 0, "lastSeen": 1674911741}, "ryonub": {"rank": "RECRUIT", "contributed": 0, "lastSeen": 1674747454}, "galsky": {"rank": "RECRUIT", "contributed": 0, "lastSeen": 1674722372}}, "joined": {"KTcompany": 1671003245, "mokan": 1672503275, "ryonub": 1673273597, "galsky": 1673795562}, "left": {}}