{"lastUpdate": 1679933739, "members": {"Debregt": {"rank": "CHIEF", "contributed": 3879225, "lastSeen": 1566426595}, "HeIldelta": {"rank": "CHIEF", "contributed": 2670452, "lastSeen": 1589072535}, "Bloppa": {"rank": "OWNER", "contributed": 6490398, "lastSeen": 1669825724}, "FireHids": {"rank": "CAPTAIN", "contributed": 412838, "lastSeen": 1679933739}, "Emify": {"rank": "RECRUIT", "contributed": 402015, "lastSeen": 1656297526}, "Yathink0": {"rank": "RECRUIT", "contributed": 7861, "lastSeen": 1648513420}}, "joined": {}, "left": {}}