{"lastUpdate": 1683828824, "members": {"Assurable": {"rank": "OWNER", "contributed": 0, "lastSeen": 1592583985}, "Bluestone380": {"rank": "RECRUIT", "contributed": 1304, "lastSeen": 1592562954}, "J5P": {"rank": "RECRUIT", "contributed": 9, "lastSeen": 1592596682}, "PengenBoker": {"rank": "RECRUIT", "contributed": 0, "lastSeen": 1683857201}, "Liqard": {"rank": "RECRUIT", "contributed": 233539, "lastSeen": 1630643495}, "otta_smack_u": {"rank": "RECRUIT", "contributed": 97563, "lastSeen": 1662794472}}, "joined": {}, "left": {}}