{"lastUpdate": 1689029060, "members": {"CottenTNT": {"rank": "OWNER", "contributed": 5966, "lastSeen": 0}, "OMGitsMax": {"rank": "CAPTAIN", "contributed": 1731, "lastSeen": 1464759367}, "Cueball18": {"rank": "RECRUIT", "contributed": 428, "lastSeen": 1447830836}, "Mc1manguest": {"rank": "RECRUIT", "contributed": 99, "lastSeen": 1440233346}, "xX_MlgPvP_Xx": {"rank": "RECRUIT", "contributed": 0, "lastSeen": 1440309265}, "Keikashii": {"rank": "CHIEF", "contributed": 17001, "lastSeen": 0}, "Architect740": {"rank": "RECRUIT", "contributed": 1554, "lastSeen": 1681475768}, "18hi": {"rank": "RECRUIT", "contributed": 806, "lastSeen": 1681456168}, "Mrderpychocolate": {"rank": "RECRUIT", "contributed": 12319, "lastSeen": 1689029060}, "Trickey": {"rank": "RECRUIT", "contributed": 17991, "lastSeen": 1577156843}, "Jaysway13": {"rank": "RECRUIT", "contributed": 50, "lastSeen": 1518073844}}, "joined": {}, "left": {}}