{"lastUpdate": 1672436439, "members": {"ldrpc": {"rank": "OWNER", "contributed": 72121, "lastSeen": 1663311169}, "Forestalien": {"rank": "CHIEF", "contributed": 487258, "lastSeen": 1663313471}, "pedrosa_sp": {"rank": "CHIEF", "contributed": 25417, "lastSeen": 1662967049}, "DankoFranko": {"rank": "CHIEF", "contributed": 980467, "lastSeen": 1672436439}, "luqitas2": {"rank": "CHIEF", "contributed": 606378, "lastSeen": 1664095389}, "PixelMarc_": {"rank": "CHIEF", "contributed": 16864, "lastSeen": 1596779088}, "Wheesy": {"rank": "RECRUIT", "contributed": 4140, "lastSeen": 1663413455}, "poggiewogs": {"rank": "RECRUIT", "contributed": 27254, "lastSeen": 1657016771}, "Flacopower1": {"rank": "RECRUIT", "contributed": 536, "lastSeen": 1662964405}, "lucation": {"rank": "RECRUIT", "contributed": 418, "lastSeen": 1663507913}, "DeezBingBongNutz": {"rank": "RECRUIT", "contributed": 61, "lastSeen": 1662944518}}, "joined": {}, "left": {}}