{"members": {"SPYROHAWK": {"rank": "OWNER", "contributed": 22330, "lastSeen": 1693520141}, "H0Y0Y0Y0Y0B0Y": {"rank": "CHIEF", "contributed": 6655394, "lastSeen": 1612667984}, "Clockwork_Entity": {"rank": "CHIEF", "contributed": 11981856, "lastSeen": 0}, "Tsuindaga": {"rank": "CHIEF", "contributed": 7962206, "lastSeen": 1626948907}}, "joined": {"EDGN": 1669155547, "Pyhaa": 1671574228, "Nitrox_Burst": 1671468643, "Maiths": 1671588515, "AstaBrouti": 1671730659, "Timeend": 1671737969, "akapvp": 1672168102, "LeKillerDu80": 1672173582, "XOLOTLY": 1672247760, "AIKO_infect0": 1672316166, "Zephylox": 1672357090, "0IlIlIlIlIlI0": 1672431374, "TechFleece_": 1672670168, "FlezerIsBack": 1672758781, "AxanneEnCulotte": 1672864797, "ApophisEnCalecon": 1672864798, "Fallen30": 1673124027, "ProgrammingGirl": 1673182458, "Ptifou": 1673405925, "BlaaawZ_": 1673565181, "GreenyPepper": 1674065626, "_anto30_": 1674592683, "DadaDaphnouche": 1674851763, "Yoruty": 1674927521, "LOLOBISCOTO": 1676081693, "TwiDev": 1676410537, "HonkaBadonka": 1676932854, "Arc001": 1677014057, "DorianLeChiant": 1677014057, "Antocow1": 1677105557, "Dodolyy": 1677372558, "D34TH_CL4W": 1677372558, "Laenthos": 1677958685, "Junichiro_S": 1677620241, "Frixal": 1678032941, "TellementFort": 1689267315, "Deltadeck": 1678036206, "Kinguu35": 1678036206, "SteveTheSheep": 1678050640, "ShiroiKoneko": 1678570758, "Exionne": 1678574423, "Tirauflan": 1678631830, "ronanore85": 1678815983, "Makaa_": 1678833535, "Ayayai_": 1678833535, "Ostore": 1679340991, "HaiseGodz": 1679605929, "007samboss": 1679696145, "jomorpheoo": 1680629822, "1mathias1": 1680713447, "BlueDrag_on": 1680813502, "pingouin_frileux": 1681658052, "SiphanoDuGhetto": 1682845863, "RatCordeur": 1683022307, "Waxer_Evios62": 1683221797, "Omegaridley350": 1683234681, "Blondine7": 1683306671, "Hekteros": 1683310358, "Watsoup": 1683555191, "ZarToX_": 1684527276, "Run4fight": 1684932737, "Zoldikuro": 1684959185, "Kayrops": 1684959186, "zombiox": 1685351424, "NarouteSenpai": 1685636107, "Balaarm": 1686217021, "Wasarikou": 1686258998, "BANCCC": 1686258998, "Shynda": 1686505233, "Lafabrique57": 1686762733, "Ouipezax": 1686785888, "CapitainHugo": 1687036497, "BeeWy": 1687119446, "BATOU154": 1687119446, "WeeGee1988": 1687241621, "Luguilu": 1687263639, "Eiiyuu": 1687450726, "Bemir_": 1687459288, "WikTuZ": 1687531402, "HVBCCLIENT": 1687539176, "FlyinRabbit": 1687545865, "Kor0kage": 1687601634, "num3sis": 1687796473, "Aka_SkiLioZ": 1687819376, "Gotch30": 1687882780, "Aguems": 1687957540, "Le_painfermier": 1688070037, "DeCaPeur2Fion": 1688247761, "Kaisao": 1688427805, "BlackBlood97470": 1688462098, "Neoxus": 1688465703, "Trash_Gamer01": 1688564124, "Liogt01": 1688577524, "DidierSuper": 1688726628, "TheDudedutapis": 1689011096, "Sn0w_Less": 1689412833, "Enryu_RedTower": 1689436208, "Nozyndeiru": 1689440375, "7617": 1689510574, "exotina": 1689949036, "IcebergVsTitanic": 1690141822, "Zelli": 1690573742, "Dragohalt": 1690591716, "Zelluw": 1690917768, "horuzaki": 1691092224, "SPYROHAWK": 1691238274, "H0Y0Y0Y0Y0B0Y": 1691238275, "Linwood_LTHR": 1691238275, "Clockwork_Entity": 1691238275, "Tsuindaga": 1691238276}, "left": {"Bratisox": {"leftAt": 1669232225, "rank": "RECRUIT"}, "Mickeydamours": {"leftAt": 1670094604, "rank": "RECRUIT"}, "jesuisrouge": {"leftAt": 1670094604, "rank": "RECRUIT"}, "Ublot": {"leftAt": 1670094604, "rank": "RECRUIT"}, "Pyhaa": {"leftAt": 1674243495, "rank": "RECRUIT"}, "KoniKun": {"leftAt": 1671662299, "rank": "RECRUIT"}, "Laeken": {"leftAt": 1671662299, "rank": "RECRUIT"}, "007samboss": {"leftAt": 1687601634, "rank": "RECRUIT"}, "Elzariia": {"leftAt": 1671662299, "rank": "RECRUITER"}, "toto101230": {"leftAt": 1671662299, "rank": "RECRUIT"}, "SupoZz_it_w4r": {"leftAt": 1671662299, "rank": "RECRUIT"}, "Denis_Brogniart_": {"leftAt": 1671662299, "rank": "RECRUIT"}, "stoonser4": {"leftAt": 1671662299, "rank": "RECRUIT"}, "coga_": {"leftAt": 1671662299, "rank": "RECRUIT"}, "Tricots_Rayes": {"leftAt": 1671662299, "rank": "RECRUIT"}, "LeCoqBeau": {"leftAt": 1671662299, "rank": "RECRUIT"}, "HeligoI": {"leftAt": 1671662299, "rank": "RECRUIT"}, "Z0lyx_": {"leftAt": 1671662299, "rank": "RECRUIT"}, "Luckypedia": {"leftAt": 1671662299, "rank": "RECRUIT"}, "Josland_": {"leftAt": 1671662299, "rank": "RECRUIT"}, "Thantara": {"leftAt": 1671662299, "rank": "RECRUIT"}, "Whaldan_": {"leftAt": 1671662299, "rank": "RECRUITER"}, "Nagorana": {"leftAt": 1671662299, "rank": "RECRUIT"}, "Noxew": {"leftAt": 1671662299, "rank": "RECRUIT"}, "pediluv": {"leftAt": 1671662299, "rank": "RECRUIT"}, "Guimle": {"leftAt": 1671662299, "rank": "RECRUIT"}, "_Raito": {"leftAt": 1671662299, "rank": "RECRUIT"}, "Azphinx": {"leftAt": 1672145711, "rank": "RECRUITER"}, "Canardingue": {"leftAt": 1672145711, "rank": "RECRUIT"}, "Mamouth": {"leftAt": 1672145711, "rank": "RECRUIT"}, "CoodBooL_": {"leftAt": 1672145711, "rank": "RECRUIT"}, "CR4T0X_": {"leftAt": 1672145711, "rank": "RECRUIT"}, "CheeeseCakke": {"leftAt": 1672168102, "rank": "RECRUIT"}, "Ssephiror": {"leftAt": 1672168102, "rank": "RECRUIT"}, "LadoSakou": {"leftAt": 1672168102, "rank": "RECRUITER"}, "UkaLysK1NG": {"leftAt": 1673118544, "rank": "RECRUIT"}, "akapvp": {"leftAt": 1673269029, "rank": "RECRUIT"}, "Frixal": {"leftAt": 1678128314, "rank": "RECRUIT"}, "Zephylox": {"leftAt": 1674861077, "rank": "RECRUIT"}, "EcolierPipelette": {"leftAt": 1674958804, "rank": "RECRUITER"}, "Zelli": {"leftAt": 1691238276, "rank": "RECRUIT"}, "lmperium": {"leftAt": 1675982356, "rank": "CAPTAIN"}, "HonkaBadonka": {"leftAt": 1676934857, "rank": "RECRUIT"}, "FrxznTheoE": {"leftAt": 1677708616, "rank": "RECRUIT"}, "Laenthos": {"leftAt": 1687884772, "rank": "RECRUIT"}, "EDGN": {"leftAt": 1678214660, "rank": "CAPTAIN"}, "XOLOTLY": {"leftAt": 1678371110, "rank": "RECRUIT"}, "LeKillerDu80": {"leftAt": 1679339596, "rank": "RECRUIT"}, "ronanore85": {"leftAt": 1680813502, "rank": "RECRUIT"}, "0IlIlIlIlIlI0": {"leftAt": 1681437792, "rank": "RECRUIT"}, "AxanneEnCulotte": {"leftAt": 1681437792, "rank": "RECRUIT"}, "ApophisEnCalecon": {"leftAt": 1681437792, "rank": "RECRUIT"}, "Fallen30": {"leftAt": 1682496681, "rank": "RECRUIT"}, "Heyoth": {"leftAt": 1684779171, "rank": "CHIEF"}, "Artifrix": {"leftAt": 1686217021, "rank": "RECRUIT"}, "riceuuh": {"leftAt": 1686217021, "rank": "RECRUIT"}, "Arc001": {"leftAt": 1686217021, "rank": "RECRUIT"}, "SiphanoDuGhetto": {"leftAt": 1686217021, "rank": "RECRUIT"}, "Atergis": {"leftAt": 1686761064, "rank": "RECRUIT"}, "D34TH_CL4W": {"leftAt": 1686761064, "rank": "RECRUIT"}, "Exionne": {"leftAt": 1686761064, "rank": "RECRUIT"}, "RatCordeur": {"leftAt": 1686761064, "rank": "RECRUIT"}, "Mecalion": {"leftAt": 1687119446, "rank": "CAPTAIN"}, "Yuuhhii_": {"leftAt": 1687119446, "rank": "RECRUIT"}, "GigaFanDeJul": {"leftAt": 1687119446, "rank": "RECRUIT"}, "MermoudLeVoleur": {"leftAt": 1687119446, "rank": "RECRUIT"}, "Sosodistrict": {"leftAt": 1687119446, "rank": "CAPTAIN"}, "Strix_Tashima": {"leftAt": 1687119446, "rank": "RECRUIT"}, "immaleks": {"leftAt": 1687119446, "rank": "RECRUIT"}, "GreenyPepper": {"leftAt": 1687119446, "rank": "RECRUIT"}, "Alex_Billi": {"leftAt": 1687601634, "rank": "STRATEGIST"}, "devilknight67": {"leftAt": 1687601634, "rank": "RECRUIT"}, "iLightniing": {"leftAt": 1687601634, "rank": "RECRUIT"}, "hugo_lyy": {"leftAt": 1687601634, "rank": "RECRUITER"}, "Timeend": {"leftAt": 1687601634, "rank": "RECRUIT"}, "AIKO_infect0": {"leftAt": 1687601634, "rank": "RECRUIT"}, "Ptifou": {"leftAt": 1687601634, "rank": "RECRUIT"}, "Junichiro_S": {"leftAt": 1687601634, "rank": "RECRUIT"}, "TellementFort": {"leftAt": 1691238276, "rank": "RECRUIT"}, "1mathias1": {"leftAt": 1687601634, "rank": "RECRUIT"}, "Wasarikou": {"leftAt": 1687601634, "rank": "RECRUIT"}, "LOLOBISCOTO": {"leftAt": 1687630873, "rank": "RECRUIT"}, "Def01t": {"leftAt": 1687884772, "rank": "CAPTAIN"}, "Dakaku": {"leftAt": 1687884772, "rank": "RECRUIT"}, "Oxgallix": {"leftAt": 1687884772, "rank": "RECRUIT"}, "PeTiT_BisCuiT_": {"leftAt": 1687884772, "rank": "RECRUIT"}, "Nitrox_Burst": {"leftAt": 1687884772, "rank": "RECRUIT"}, "TechFleece_": {"leftAt": 1687884772, "rank": "RECRUIT"}, "FlezerIsBack": {"leftAt": 1687884772, "rank": "RECRUIT"}, "_anto30_": {"leftAt": 1687884772, "rank": "RECRUIT"}, "TwiDev": {"leftAt": 1687884772, "rank": "RECRUIT"}, "Antocow1": {"leftAt": 1687884772, "rank": "RECRUIT"}, "Deltadeck": {"leftAt": 1687967090, "rank": "RECRUIT"}, "Tirauflan": {"leftAt": 1687967090, "rank": "RECRUIT"}, "Ayayai_": {"leftAt": 1687967090, "rank": "RECRUIT"}, "BlueDrag_on": {"leftAt": 1687967090, "rank": "RECRUIT"}, "pingouin_frileux": {"leftAt": 1687967090, "rank": "RECRUIT"}, "Zekrom35": {"leftAt": 1688640342, "rank": "RECRUITER"}, "Exutoire": {"leftAt": 1688640342, "rank": "CAPTAIN"}, "lilian5112": {"leftAt": 1691238276, "rank": "CHIEF"}, "Squimble": {"leftAt": 1691238276, "rank": "CHIEF"}, "Hunter_viperz": {"leftAt": 1691238276, "rank": "RECRUIT"}, "Sylvaacken": {"leftAt": 1691238276, "rank": "CHIEF"}, "Just_Jambon": {"leftAt": 1691238276, "rank": "CAPTAIN"}, "Endermity": {"leftAt": 1691238276, "rank": "CAPTAIN"}, "Sire_Maou": {"leftAt": 1691238276, "rank": "OWNER"}, "Leyhearth": {"leftAt": 1691238276, "rank": "RECRUIT"}, "rorororo1999": {"leftAt": 1691238276, "rank": "RECRUITER"}, "Caroze": {"leftAt": 1691238276, "rank": "RECRUITER"}, "Slasheuuu": {"leftAt": 1691238276, "rank": "RECRUIT"}, "mathcroft": {"leftAt": 1691238276, "rank": "STRATEGIST"}, "Redmod": {"leftAt": 1691238276, "rank": "STRATEGIST"}, "JeanGuyGabriel": {"leftAt": 1691238276, "rank": "CHIEF"}, "scio_nihil_": {"leftAt": 1691238276, "rank": "CHIEF"}, "oMyGod": {"leftAt": 1691238276, "rank": "CHIEF"}, "Mistmemo": {"leftAt": 1691238276, "rank": "CAPTAIN"}, "Big_Togn0": {"leftAt": 1691238276, "rank": "STRATEGIST"}, "Filippo_Fabbri": {"leftAt": 1691238276, "rank": "CHIEF"}, "LaTiika": {"leftAt": 1691238276, "rank": "RECRUITER"}, "Maiths": {"leftAt": 1691238276, "rank": "RECRUIT"}, "AstaBrouti": {"leftAt": 1691238276, "rank": "RECRUIT"}, "ProgrammingGirl": {"leftAt": 1691238276, "rank": "RECRUIT"}, "BlaaawZ_": {"leftAt": 1691238276, "rank": "RECRUIT"}, "DadaDaphnouche": {"leftAt": 1691238276, "rank": "RECRUIT"}, "Yoruty": {"leftAt": 1691238276, "rank": "RECRUIT"}, "DorianLeChiant": {"leftAt": 1691238276, "rank": "RECRUIT"}, "Dodolyy": {"leftAt": 1691238276, "rank": "RECRUIT"}, "Kinguu35": {"leftAt": 1691238276, "rank": "RECRUIT"}, "SteveTheSheep": {"leftAt": 1691238276, "rank": "RECRUIT"}, "ShiroiKoneko": {"leftAt": 1691238276, "rank": "RECRUIT"}, "Makaa_": {"leftAt": 1691238276, "rank": "RECRUIT"}, "Ostore": {"leftAt": 1691238276, "rank": "RECRUIT"}, "HaiseGodz": {"leftAt": 1691238276, "rank": "RECRUIT"}, "jomorpheoo": {"leftAt": 1691238276, "rank": "RECRUIT"}, "Waxer_Evios62": {"leftAt": 1691238276, "rank": "RECRUIT"}, "Omegaridley350": {"leftAt": 1691238276, "rank": "RECRUIT"}, "Blondine7": {"leftAt": 1691238276, "rank": "RECRUIT"}, "Hekteros": {"leftAt": 1691238276, "rank": "RECRUITER"}, "Watsoup": {"leftAt": 1691238276, "rank": "RECRUIT"}, "ZarToX_": {"leftAt": 1691238276, "rank": "RECRUIT"}, "Run4fight": {"leftAt": 1691238276, "rank": "RECRUIT"}, "Zoldikuro": {"leftAt": 1691238276, "rank": "RECRUIT"}, "Kayrops": {"leftAt": 1691238276, "rank": "RECRUIT"}, "zombiox": {"leftAt": 1691238276, "rank": "RECRUIT"}, "NarouteSenpai": {"leftAt": 1691238276, "rank": "RECRUIT"}, "Balaarm": {"leftAt": 1691238276, "rank": "RECRUIT"}, "BANCCC": {"leftAt": 1691238276, "rank": "RECRUIT"}, "Shynda": {"leftAt": 1691238276, "rank": "RECRUIT"}, "Lafabrique57": {"leftAt": 1691238276, "rank": "RECRUIT"}, "Ouipezax": {"leftAt": 1691238276, "rank": "RECRUIT"}, "CapitainHugo": {"leftAt": 1691238276, "rank": "RECRUIT"}, "BeeWy": {"leftAt": 1691238276, "rank": "RECRUIT"}, "BATOU154": {"leftAt": 1691238276, "rank": "RECRUIT"}, "WeeGee1988": {"leftAt": 1691238276, "rank": "RECRUIT"}, "Luguilu": {"leftAt": 1691238276, "rank": "RECRUIT"}, "Eiiyuu": {"leftAt": 1691238276, "rank": "RECRUIT"}, "Bemir_": {"leftAt": 1691238276, "rank": "RECRUIT"}, "WikTuZ": {"leftAt": 1691238276, "rank": "RECRUIT"}, "HVBCCLIENT": {"leftAt": 1691238276, "rank": "STRATEGIST"}, "FlyinRabbit": {"leftAt": 1691238276, "rank": "RECRUIT"}, "Kor0kage": {"leftAt": 1691238276, "rank": "RECRUIT"}, "num3sis": {"leftAt": 1691238276, "rank": "RECRUIT"}, "Aka_SkiLioZ": {"leftAt": 1691238276, "rank": "RECRUITER"}, "Gotch30": {"leftAt": 1691238276, "rank": "RECRUIT"}, "Aguems": {"leftAt": 1691238276, "rank": "RECRUIT"}, "Le_painfermier": {"leftAt": 1691238276, "rank": "RECRUIT"}, "DeCaPeur2Fion": {"leftAt": 1691238276, "rank": "RECRUIT"}, "Kaisao": {"leftAt": 1691238276, "rank": "RECRUIT"}, "BlackBlood97470": {"leftAt": 1691238276, "rank": "RECRUIT"}, "Neoxus": {"leftAt": 1691238276, "rank": "RECRUIT"}, "Trash_Gamer01": {"leftAt": 1691238276, "rank": "RECRUIT"}, "Liogt01": {"leftAt": 1691238276, "rank": "RECRUIT"}, "DidierSuper": {"leftAt": 1691238276, "rank": "RECRUIT"}, "TheDudedutapis": {"leftAt": 1691238276, "rank": "RECRUIT"}, "Sn0w_Less": {"leftAt": 1691238276, "rank": "RECRUIT"}, "Enryu_RedTower": {"leftAt": 1691238276, "rank": "RECRUIT"}, "Nozyndeiru": {"leftAt": 1691238276, "rank": "RECRUIT"}, "7617": {"leftAt": 1691238276, "rank": "CAPTAIN"}, "exotina": {"leftAt": 1691238276, "rank": "RECRUIT"}, "IcebergVsTitanic": {"leftAt": 1691238276, "rank": "RECRUIT"}, "Dragohalt": {"leftAt": 1691238276, "rank": "RECRUIT"}, "Zelluw": {"leftAt": 1691238276, "rank": "RECRUIT"}, "horuzaki": {"leftAt": 1691238276, "rank": "RECRUIT"}, "Linwood_LTHR": {"leftAt": 1693169029, "rank": "CHIEF"}}, "lastUpdate": 1693520141}