{"lastUpdate": 1673683878, "members": {"NathanSLao": {"rank": "CAPTAIN", "contributed": 730233, "lastSeen": 1629201326}, "BuffaloRanch21": {"rank": "RECRUIT", "contributed": 92, "lastSeen": 1603957053}, "TheAtkins": {"rank": "RECRUIT", "contributed": 1039, "lastSeen": 1435134787}, "TairaBacca": {"rank": "CAPTAIN", "contributed": 1908575, "lastSeen": 1434026912}, "Platy_": {"rank": "CAPTAIN", "contributed": 736, "lastSeen": 1547890103}, "TheAlienPlatypus": {"rank": "RECRUIT", "contributed": 1971, "lastSeen": 1551519831}, "Legenfighter": {"rank": "OWNER", "contributed": 1620299, "lastSeen": 0}, "deathtalking": {"rank": "RECRUIT", "contributed": 312, "lastSeen": 1494218879}, "Sexq": {"rank": "RECRUIT", "contributed": 0, "lastSeen": 1553165702}, "Domenator02": {"rank": "RECRUIT", "contributed": 13001, "lastSeen": 1603034140}, "vMeza": {"rank": "STRATEGIST", "contributed": 20996839, "lastSeen": 1663143271}, "Jolanquious": {"rank": "RECRUIT", "contributed": 9, "lastSeen": 1592997228}, "Siddd": {"rank": "CHIEF", "contributed": 199940507, "lastSeen": 1673683878}, "StrideMan": {"rank": "RECRUIT", "contributed": 30, "lastSeen": 1664884246}, "Baguette_Bandit": {"rank": "RECRUIT", "contributed": 1062, "lastSeen": 1603156980}, "crafted_2002": {"rank": "RECRUIT", "contributed": 4007, "lastSeen": 1603036314}, "ShayAvni": {"rank": "STRATEGIST", "contributed": 0, "lastSeen": 1672116017}}, "joined": {"DefectiveTanky": 1668552075, "Onsii": 1669947473, "NathanSLao": 1669970300, "BuffaloRanch21": 1669970300, "TheAtkins": 1669970301, "TairaBacca": 1669970301, "Platy_": 1669970301, "TheAlienPlatypus": 1669970301, "Legenfighter": 1669970302, "deathtalking": 1669970302, "Sexq": 1669970302, "Domenator02": 1669970302, "vMeza": 1669970302, "Jolanquious": 1669970303, "Siddd": 1669970303, "StrideMan": 1669970303, "Baguette_Bandit": 1669970303, "crafted_2002": 1669970303, "ShayAvni": 1672114272}, "left": {"LaoMu": {"leftAt": 1669970303, "rank": "CAPTAIN"}, "XXfordazXX": {"leftAt": 1669970303, "rank": "CAPTAIN"}, "Anilio": {"leftAt": 1669970303, "rank": "RECRUIT"}, "Willikers": {"leftAt": 1669970303, "rank": "RECRUIT"}, "Gigi589": {"leftAt": 1669970303, "rank": "RECRUIT"}, "GenkiXP": {"leftAt": 1669970303, "rank": "RECRUIT"}, "UntameableWolf12": {"leftAt": 1669970303, "rank": "RECRUIT"}, "iHitzYou": {"leftAt": 1669970303, "rank": "RECRUIT"}, "peachi_vi": {"leftAt": 1669970303, "rank": "RECRUIT"}, "Z3R0iC": {"leftAt": 1669970303, "rank": "RECRUIT"}, "JohnietheJiraph": {"leftAt": 1669970303, "rank": "OWNER"}, "DefectiveTanky": {"leftAt": 1669970303, "rank": "RECRUIT"}, "Onsii": {"leftAt": 1669970303, "rank": "RECRUIT"}}}