{"lastUpdate": 1672748222, "members": {"Rosebyggeren": {"rank": "RECRUIT", "contributed": 2150005, "lastSeen": 1672748222}, "other_brothers": {"rank": "RECRUITER", "contributed": 205498, "lastSeen": 1664083801}, "PhatGolo": {"rank": "CHIEF", "contributed": 8136, "lastSeen": 1665979575}, "EarthHDD": {"rank": "RECRUIT", "contributed": 309715, "lastSeen": 1670445408}, "Hexgolo": {"rank": "OWNER", "contributed": 16752211, "lastSeen": 1670447371}, "Taraneas": {"rank": "CHIEF", "contributed": 55920027, "lastSeen": 1670958504}, "Billminator": {"rank": "RECRUIT", "contributed": 725, "lastSeen": 1665901192}, "Jammjamm": {"rank": "RECRUIT", "contributed": 140, "lastSeen": 1665787129}, "Foffan": {"rank": "RECRUIT", "contributed": 262, "lastSeen": 1670353680}}, "joined": {"RenNicht": 1668339499, "Bene123456789": 1668365178, "N1ZeLeon": 1668368300, "Rosebyggeren": 1669143002, "other_brothers": 1669143003, "PhatGolo": 1669143003, "EarthHDD": 1669143003, "Hexgolo": 1669143003, "Taraneas": 1669143003, "Billminator": 1669143004, "Jammjamm": 1669143004, "Foffan": 1669934242}, "left": {"Columbo_2007": {"leftAt": 1669143004, "rank": "OWNER"}, "KaktusBTW": {"leftAt": 1669143004, "rank": "CHIEF"}, "Omega_Athene": {"leftAt": 1669143004, "rank": "CHIEF"}, "RenNicht": {"leftAt": 1669143004, "rank": "STRATEGIST"}, "Bene123456789": {"leftAt": 1669143004, "rank": "RECRUIT"}, "N1ZeLeon": {"leftAt": 1669143004, "rank": "STRATEGIST"}}}