{"members": {"Xales27": {"rank": "CHIEF", "contributed": 916115, "lastSeen": 1688470935}, "IamRainb0w": {"rank": "OWNER", "contributed": 605959273, "lastSeen": 1688470935}, "Fadopastor": {"rank": "CHIEF", "contributed": 923647243, "lastSeen": 1688470935}, "Majkel_Tarotti": {"rank": "RECRUITER", "contributed": 1651329, "lastSeen": 1641044105}, "ShiraUVVU": {"rank": "STRATEGIST", "contributed": 43138, "lastSeen": 1666801607}, "Max3690": {"rank": "RECRUIT", "contributed": 1390, "lastSeen": 1667758872}, "snakesalad": {"rank": "RECRUITER", "contributed": 5129, "lastSeen": 1644276258}, "Kamikazi": {"rank": "CAPTAIN", "contributed": 83956050, "lastSeen": 1665287731}, "Guff711": {"rank": "RECRUIT", "contributed": 36886, "lastSeen": 1683365780}, "R4sheg": {"rank": "RECRUIT", "contributed": 291402, "lastSeen": 1678563569}, "Frebbie": {"rank": "RECRUITER", "contributed": 9780400, "lastSeen": 1672175553}, "KarateKidGamer1": {"rank": "CAPTAIN", "contributed": 249301991, "lastSeen": 1669477088}, "Lasercutie": {"rank": "RECRUIT", "contributed": 617138, "lastSeen": 1685451343}, "ABel_Jarvis": {"rank": "RECRUIT", "contributed": 24822, "lastSeen": 1685441464}, "Dallas_4244": {"rank": "RECRUITER", "contributed": 18773058, "lastSeen": 1669559813}, "ItsKingJunus": {"rank": "RECRUITER", "contributed": 6263385, "lastSeen": 1688192174}, "SexieTexie": {"rank": "CAPTAIN", "contributed": 74666649, "lastSeen": 1667739296}, "HATOLA": {"rank": "RECRUITER", "contributed": 22020446, "lastSeen": 1676814061}, "Sempaichik": {"rank": "RECRUIT", "contributed": 0, "lastSeen": 1666799318}, "mcfiletmc": {"rank": "RECRUIT", "contributed": 33791, "lastSeen": 1666563399}, "Tippie_": {"rank": "RECRUIT", "contributed": 0, "lastSeen": 1675078500}, "FGinkyZ": {"rank": "RECRUITER", "contributed": 3762182, "lastSeen": 1667632295}, "Jendabeat": {"rank": "RECRUIT", "contributed": 5530, "lastSeen": 1667148175}, "Schevenko": {"rank": "RECRUITER", "contributed": 3776653, "lastSeen": 1670632571}, "samcas1930": {"rank": "RECRUIT", "contributed": 10468, "lastSeen": 1677953841}, "Siba88": {"rank": "RECRUIT", "contributed": 0, "lastSeen": 1675636596}}, "joined": {"Siba88": 1668272068, "jerrbewr": 1668390338, "Amnezjanin": 1668532743}, "left": {"Altenterevon": {"leftAt": 1671289961, "rank": "RECRUITER"}, "SoulCrush3r": {"leftAt": 1672385707, "rank": "RECRUITER"}, "ShadowCyclone": {"leftAt": 1672973942, "rank": "RECRUIT"}, "Lyrun": {"leftAt": 1674916692, "rank": "STRATEGIST"}, "ThoughtBlob": {"leftAt": 1675613651, "rank": "RECRUITER"}, "spokyg": {"leftAt": 1676328034, "rank": "RECRUITER"}, "Eiryu": {"leftAt": 1678313597, "rank": "RECRUITER"}, "William_N": {"leftAt": 1681618478, "rank": "RECRUIT"}, "Utor_": {"leftAt": 1685079500, "rank": "RECRUITER"}, "Itz_Dxrrk": {"leftAt": 1685079500, "rank": "RECRUITER"}, "God_": {"leftAt": 1687891769, "rank": "RECRUIT"}, "SwordLewis": {"leftAt": 1687891769, "rank": "RECRUIT"}, "BrainDeadExe": {"leftAt": 1687891769, "rank": "RECRUIT"}, "Exiledleopard": {"leftAt": 1687891769, "rank": "RECRUIT"}, "MattieHD": {"leftAt": 1687891769, "rank": "RECRUITER"}, "D1wid15": {"leftAt": 1687891769, "rank": "RECRUITER"}, "Elixician": {"leftAt": 1687891769, "rank": "RECRUIT"}, "Sashee": {"leftAt": 1687891769, "rank": "RECRUIT"}, "Absolute17": {"leftAt": 1687891769, "rank": "RECRUIT"}, "vihoman": {"leftAt": 1687891769, "rank": "RECRUITER"}, "jerrbewr": {"leftAt": 1687891769, "rank": "RECRUIT"}, "Amnezjanin": {"leftAt": 1688329278, "rank": "RECRUIT"}}, "lastUpdate": 1688470935}