{"lastUpdate": 1698146381, "members": {"Mythicwhen": {"rank": "OWNER", "contributed": 3212246, "lastSeen": 1696771405}, "Ian0822": {"rank": "CHIEF", "contributed": 0, "lastSeen": 1698146381}, "tcdcbs": {"rank": "RECRUIT", "contributed": 0, "lastSeen": 1694877468}, "Tletur": {"rank": "RECRUIT", "contributed": 2356644, "lastSeen": 1695041766}, "MMG_Rich": {"rank": "RECRUIT", "contributed": 0, "lastSeen": 1694875278}, "Ouroar": {"rank": "RECRUIT", "contributed": 0, "lastSeen": 1695522345}, "Ryanchaoboy": {"rank": "CAPTAIN", "contributed": 1704795, "lastSeen": 1697354373}}, "joined": {"Ian0822": 1694850105, "tcdcbs": 1694852180, "Tletur": 1694870149, "MMG_Rich": 1694871661, "Ouroar": 1694871662, "MMG_Su": 1694873746, "Ryanchaoboy": 1694875278}, "left": {"MMG_Su": {"leftAt": 1697377694, "rank": "RECRUIT"}}}